{
  "_meta": {
    "do_not_edit": true,
    "generated_by": "scripts/generate_sheets_schema.py",
    "schema_version": 1,
    "sources": [
      "create_agent_sheets.AGENT_SHEET_HEADERS",
      "sheets_manager.TIMELINE_LIVE_COLS",
      "post_analysis stable-subset (authored) + config forward-window"
    ]
  },
  "sheets": {
    "agent_scorecard": {
      "columns": [
        "Date",
        "Agent",
        "Facts",
        "Anomaly_Count",
        "Anomaly_High",
        "Anomaly_Detail",
        "Generated_At"
      ],
      "mode": "exact",
      "source": "AGENT_SHEET_HEADERS"
    },
    "borrow_coverage": {
      "columns": [
        "CheckDate",
        "CheckTime",
        "ScannedUniverse",
        "WithBorrowData",
        "PctWithBorrowData",
        "ShortableCount",
        "PctShortable",
        "Source"
      ],
      "mode": "exact",
      "source": "AGENT_SHEET_HEADERS"
    },
    "borrow_data": {
      "columns": [
        "Ticker",
        "CheckDate",
        "CheckTime",
        "IsShortable",
        "IsETB",
        "IsHTB",
        "BorrowFeePct",
        "SharesAvailable",
        "Source"
      ],
      "mode": "exact",
      "source": "AGENT_SHEET_HEADERS"
    },
    "config_history": {
      "columns": [
        "ChangeID",
        "Timestamp",
        "ChangedBy",
        "ChangeType",
        "Parameter",
        "OldValue",
        "NewValue",
        "Reason",
        "SuggestionID",
        "ApprovedBy"
      ],
      "mode": "exact",
      "source": "AGENT_SHEET_HEADERS"
    },
    "decision_log": {
      "columns": [
        "DecisionID",
        "Timestamp",
        "Ticker",
        "SignalSource",
        "AgentMode",
        "Action",
        "Reason",
        "SkipReason",
        "Price",
        "Volume",
        "MarketCap",
        "Float",
        "Open",
        "High",
        "Low",
        "Score",
        "MxV",
        "RunUp",
        "ATRX",
        "RSI",
        "TypicalPriceDist",
        "REL_VOL",
        "PriceVsSMA20",
        "ScanChange",
        "FloatPct",
        "DecisionTimeMs",
        "ConfidenceScore",
        "IsShortable",
        "BorrowFee",
        "BorrowAvailable",
        "LocateStatus",
        "PositionSizeUSD",
        "Quantity",
        "TPPrice",
        "SLPrice",
        "ExistingPosition",
        "BuyingPower",
        "ColdStartConcurrentLeft",
        "ColdStartDailyLeft",
        "OrderID",
        "OrderStatus",
        "ExecutionPrice"
      ],
      "mode": "exact",
      "source": "AGENT_SHEET_HEADERS"
    },
    "market_context": {
      "columns": [
        "Timestamp",
        "SPY_Open",
        "SPY_Close",
        "SPY_Direction",
        "IWM_Open",
        "IWM_Close",
        "IWM_Direction",
        "VIX_Close",
        "VIX_Level",
        "Market_Regime",
        "Errors"
      ],
      "mode": "exact",
      "source": "AGENT_SHEET_HEADERS"
    },
    "news_findings": {
      "columns": [
        "Timestamp",
        "Ticker",
        "Has_Material_News",
        "EDGAR_Filing_Count",
        "EDGAR_Latest_Form",
        "EDGAR_Latest_Date",
        "EDGAR_All_Filings",
        "Finnhub_News_Count",
        "Finnhub_Latest_Headline",
        "Finnhub_All_News",
        "Errors"
      ],
      "mode": "exact",
      "source": "AGENT_SHEET_HEADERS"
    },
    "paper_portfolio": {
      "columns": [
        "PositionID",
        "Ticker",
        "EntryDate",
        "EntryTime",
        "EntryPrice",
        "Quantity",
        "PositionSizeUSD",
        "Side",
        "EntryOrderID",
        "TPOrderID",
        "SLOrderID",
        "TPPrice",
        "SLPrice",
        "CurrentPrice",
        "UnrealizedPnL",
        "UnrealizedPnLPct",
        "Status",
        "ExitPrice",
        "ExitDate",
        "ExitTime",
        "ExitReason",
        "RealizedPnL",
        "RealizedPnLPct",
        "LastUpdated",
        "DataQuality"
      ],
      "mode": "exact",
      "source": "AGENT_SHEET_HEADERS"
    },
    "pending_suggestions": {
      "columns": [
        "SuggestionID",
        "GeneratedDate",
        "WeekOf",
        "Type",
        "Description",
        "Reasoning",
        "Confidence",
        "AffectedMetric",
        "CurrentValue",
        "ProposedValue",
        "Status",
        "UserResponse",
        "ResponseDate",
        "SampleSize"
      ],
      "mode": "exact",
      "source": "AGENT_SHEET_HEADERS"
    },
    "post_analysis": {
      "forward_optional": [
        "D6_Close",
        "D6_Low",
        "D7_Close",
        "D7_Low",
        "D8_Close",
        "D8_Low",
        "D9_Close",
        "D9_Low",
        "D10_Close",
        "D10_Low",
        "D11_Close",
        "D11_Low",
        "D12_Close",
        "D12_Low",
        "D13_Close",
        "D13_Low",
        "D14_Close",
        "D14_Low",
        "D15_Close",
        "D15_Low",
        "D16_Close",
        "D16_Low",
        "D17_Close",
        "D17_Low",
        "D18_Close",
        "D18_Low",
        "D19_Close",
        "D19_Low",
        "D20_Close",
        "D20_Low",
        "D21_Close",
        "D21_Low",
        "D22_Close",
        "D22_Low",
        "D23_Close",
        "D23_Low",
        "D24_Close",
        "D24_Low",
        "D25_Close",
        "D25_Low"
      ],
      "mode": "required_subset",
      "required": [
        "Ticker",
        "ScanDate",
        "Score",
        "ScanPrice",
        "score_version"
      ],
      "source": "post_analysis stable-subset (authored) + config forward-window"
    },
    "postmortems": {
      "columns": [
        "PostmortemID",
        "PositionID",
        "Ticker",
        "EntryDate",
        "EntryPrice",
        "ScoreAtEntry",
        "MetricsAtEntry",
        "ExitDate",
        "ExitPrice",
        "PnLPct",
        "ExitReason",
        "DurationHours",
        "MaxFavorable",
        "MaxAdverse",
        "AutoLessons",
        "GeneratedAt",
        "ScoreVersion"
      ],
      "mode": "exact",
      "source": "AGENT_SHEET_HEADERS"
    },
    "score_analytics": {
      "columns": [
        "Date",
        "AnalysisType",
        "Period",
        "TotalTrades",
        "WinRate",
        "TotalPnL",
        "AvgPnL",
        "MedianPnL",
        "WinRate_60_70",
        "WinRate_70_80",
        "WinRate_80_90",
        "WinRate_90_plus",
        "Corr_MxV",
        "Corr_RunUp",
        "Corr_ATRX",
        "Corr_RSI",
        "Corr_TypicalPriceDist",
        "Corr_ScanChange",
        "Corr_REL_VOL",
        "StrongestPredictor",
        "WeakestPredictor",
        "SurpriseFinding",
        "Recommendation",
        "SampleSize",
        "GeneratedAt"
      ],
      "mode": "exact",
      "source": "AGENT_SHEET_HEADERS"
    },
    "sentinel_events": {
      "columns": [
        "Timestamp",
        "EventType",
        "Severity",
        "Component",
        "Message",
        "Details",
        "ActionTaken"
      ],
      "mode": "exact",
      "source": "AGENT_SHEET_HEADERS"
    },
    "skip_summary": {
      "columns": [
        "Timestamp",
        "RunID",
        "SkipReason",
        "Count",
        "Tickers",
        "ScoreMin",
        "ScoreMax"
      ],
      "mode": "exact",
      "source": "AGENT_SHEET_HEADERS"
    },
    "system_events": {
      "columns": [
        "Timestamp",
        "EventType",
        "Severity",
        "Component",
        "Message",
        "Details",
        "ActionTaken"
      ],
      "mode": "exact",
      "source": "AGENT_SHEET_HEADERS"
    },
    "timeline_live": {
      "columns": [
        "Date",
        "ScanTime",
        "Ticker",
        "Price",
        "Volume",
        "MarketCap",
        "Score",
        "MxV",
        "RunUp",
        "REL_VOL",
        "Change",
        "RSI",
        "ATRX",
        "Gap",
        "TypicalPriceDist",
        "PriceToHigh",
        "PriceTo52WHigh",
        "Float%",
        "Open_price",
        "PrevClose",
        "High_today",
        "Low_today",
        "TypicalPrice",
        "ATR14_raw",
        "Week52High",
        "SharesOutstanding",
        "AvgVolume",
        "FloatShares"
      ],
      "mode": "exact",
      "source": "TIMELINE_LIVE_COLS"
    },
    "weekly_summary": {
      "columns": [
        "WeekOf",
        "Trades",
        "Wins",
        "Losses",
        "WinRate",
        "TotalPnL",
        "AvgWin",
        "AvgLoss",
        "Enters",
        "Skips",
        "TickersChecked",
        "Anomalies",
        "Conflicts",
        "Conclusion",
        "SampleSizeFlag",
        "GeneratedAt"
      ],
      "mode": "exact",
      "source": "AGENT_SHEET_HEADERS"
    }
  }
}
